luigi_gadd/__init__.py
luigi_gadd/auto_rerun_task.py
luigi_gadd/dynamic.py
luigi_gadd/multi_target_manager.py
luigi_gadd-0.3.0.dist-info/LICENSE
luigi_gadd-0.3.0.dist-info/WHEEL
luigi_gadd-0.3.0.dist-info/METADATA
luigi_gadd-0.3.0.dist-info/RECORD
