Metadata-Version: 2.1
Name: luigi-gadd
Version: 0.3.0
Summary: Provides additional functionality to make Luigi more flexible
Home-page: https://github.com/mikelynch/luigi-gadd
License: MIT
Author: Mike Lynch
Author-email: me@msl.sh
Requires-Python: >=3.6,<4.0
Classifier: License :: OSI Approved :: MIT License
Classifier: Programming Language :: Python :: 3
Classifier: Programming Language :: Python :: 3.6
Classifier: Programming Language :: Python :: 3.7
Classifier: Programming Language :: Python :: 3.8
Classifier: Programming Language :: Python :: 3.9
Requires-Dist: luigi (>=3.0,<4.0)
Project-URL: Repository, https://github.com/mikelynch/luigi-gadd
